<?xml version="1.0" encoding="utf-8" ?>
<dwsync>
<file name="_all-skins.css" server="ftp.tropicalcastanhas.com.br" local="131371737990146117" remote="131333971800000000" Dst="1" />
<file name="skin-black-light.css" server="ftp.tropicalcastanhas.com.br" local="131371737995811646" remote="131333971800000000" Dst="1" />
<file name="_all-skins.min.css" server="ftp.tropicalcastanhas.com.br" local="131371737996777027" remote="131333971800000000" Dst="1" />
<file name="skin-black-light.min.css" server="ftp.tropicalcastanhas.com.br" local="131371737997037209" remote="131333971800000000" Dst="1" />
<file name="skin-black.css" server="ftp.tropicalcastanhas.com.br" local="131371738004011565" remote="131333971800000000" Dst="1" />
<file name="skin-black.min.css" server="ftp.tropicalcastanhas.com.br" local="131371738004061682" remote="131333971800000000" Dst="1" />
<file name="skin-blue-light.css" server="ftp.tropicalcastanhas.com.br" local="131371738005153760" remote="131333971800000000" Dst="1" />
<file name="skin-blue.css" server="ftp.tropicalcastanhas.com.br" local="131371738010739660" remote="131333971800000000" Dst="1" />
<file name="skin-blue-light.min.css" server="ftp.tropicalcastanhas.com.br" local="131371738011417879" remote="131333971800000000" Dst="1" />
<file name="skin-blue.min.css" server="ftp.tropicalcastanhas.com.br" local="131371738012672527" remote="131333971800000000" Dst="1" />
<file name="skin-green-light.css" server="ftp.tropicalcastanhas.com.br" local="131371738017444065" remote="131333971800000000" Dst="1" />
<file name="skin-green-light.min.css" server="ftp.tropicalcastanhas.com.br" local="131371738019536493" remote="131333971800000000" Dst="1" />
<file name="skin-green.css" server="ftp.tropicalcastanhas.com.br" local="131371738020757360" remote="131333971800000000" Dst="1" />
<file name="skin-green.min.css" server="ftp.tropicalcastanhas.com.br" local="131371738024590084" remote="131333971800000000" Dst="1" />
<file name="skin-purple-light.min.css" server="ftp.tropicalcastanhas.com.br" local="131371738027412089" remote="131333971800000000" Dst="1" />
<file name="skin-purple-light.css" server="ftp.tropicalcastanhas.com.br" local="131371738028282699" remote="131333971800000000" Dst="1" />
<file name="skin-purple.css" server="ftp.tropicalcastanhas.com.br" local="131371738032355593" remote="131333971800000000" Dst="1" />
<file name="skin-purple.min.css" server="ftp.tropicalcastanhas.com.br" local="131371738034665357" remote="131333971800000000" Dst="1" />
<file name="skin-red-light.css" server="ftp.tropicalcastanhas.com.br" local="131371738036305695" remote="131333971800000000" Dst="1" />
<file name="skin-red-light.min.css" server="ftp.tropicalcastanhas.com.br" local="131371738039165857" remote="131333971800000000" Dst="1" />
<file name="skin-red.css" server="ftp.tropicalcastanhas.com.br" local="131371738042506341" remote="131333971800000000" Dst="1" />
<file name="skin-red.min.css" server="ftp.tropicalcastanhas.com.br" local="131371738045052043" remote="131333971800000000" Dst="1" />
<file name="skin-yellow-light.css" server="ftp.tropicalcastanhas.com.br" local="131371738046235988" remote="131333971800000000" Dst="1" />
<file name="skin-yellow-light.min.css" server="ftp.tropicalcastanhas.com.br" local="131371738049718584" remote="131333971800000000" Dst="1" />
<file name="skin-yellow.min.css" server="ftp.tropicalcastanhas.com.br" local="131371738053202379" remote="131333971800000000" Dst="1" />
<file name="skin-yellow.css" server="ftp.tropicalcastanhas.com.br" local="131371738053383530" remote="131333971800000000" Dst="1" />
</dwsync>